[
  {"name":"flare.month.JANUARY","size":1000,"imports":[]},
  {"name":"flare.month.FEBRUARY","size":1000,"imports":[]},
  {"name":"flare.month.MARCH","size":1000,"imports":[]},
  {"name":"flare.month.APRIL","size":1000,"imports":[]},
  {"name":"flare.month.MAY","size":1000,"imports":[]},
  {"name":"flare.month.JUNE","size":1000,"imports":[]},
  {"name":"flare.month.JULY","size":1000,"imports":[]},
  {"name":"flare.month.AUGUST","size":1000,"imports":[]},
  {"name":"flare.month.SEPTEMBER","size":1000,"imports":[]},
  {"name":"flare.month.OCTOBER","size":1000,"imports":[]},
  {"name":"flare.month.NOVEMBER","size":1000,"imports":[]},
  {"name":"flare.month.DECEMBER","size":1000,"imports":[]},

  {"name":"flare.crop.Asparagus","size":3534,"imports":["flare.month.JANUARY","flare.month.FEBRUARY","flare.month.MARCH"]},
  {"name":"flare.crop.Beans.bush","size":3534,"imports":["flare.month.MARCH","flare.month.APRIL","flare.month.MAY","flare.month.APRIL","flare.month.MAY","flare.month.JUNE","flare.month.JULY","flare.month.AUGUST","flare.month.SEPTEMBER"]},
  {"name":"flare.crop.Beans.pole","size":3534,"imports":["flare.month.MARCH","flare.month.APRIL","flare.month.MAY","flare.month.APRIL","flare.month.MAY","flare.month.JUNE","flare.month.JULY","flare.month.AUGUST"]},
  {"name":"flare.crop.Beets","size":3534,"imports":["flare.month.JANUARY","flare.month.FEBRUARY","flare.month.MARCH","flare.month.APRIL","flare.month.MAY","flare.month.APRIL","flare.month.MAY","flare.month.JUNE","flare.month.JULY","flare.month.AUGUST","flare.month.SEPTEMBER","flare.month.OCTOBER","flare.month.NOVEMBER","flare.month.DECEMBER"]},
  {"name":"flare.crop.Broccoli","size":3534,"imports":["flare.month.JANUARY","flare.month.FEBRUARY","flare.month.MARCH","flare.month.SEPTEMBER","flare.month.OCTOBER","flare.month.NOVEMBER","flare.month.DECEMBER"]},
  {"name":"flare.crop.BrusselsSprouts","size":3534,"imports":["flare.month.JANUARY","flare.month.FEBRUARY","flare.month.MARCH","flare.month.SEPTEMBER","flare.month.OCTOBER","flare.month.NOVEMBER","flare.month.DECEMBER"]},
  {"name":"flare.crop.Cabbage","size":3534,"imports":["flare.month.JANUARY","flare.month.FEBRUARY","flare.month.MARCH","flare.month.OCTOBER","flare.month.NOVEMBER","flare.month.DECEMBER"]},
  {"name":"flare.crop.Cantaloupe","size":3534,"imports":["flare.month.APRIL","flare.month.MAY","flare.month.JUNE"]},
  {"name":"flare.crop.Carrots","size":3534,"imports":["flare.month.JANUARY","flare.month.FEBRUARY","flare.month.MARCH","flare.month.APRIL","flare.month.MAY","flare.month.APRIL","flare.month.MAY","flare.month.JUNE","flare.month.JULY","flare.month.AUGUST","flare.month.SEPTEMBER","flare.month.OCTOBER","flare.month.NOVEMBER","flare.month.DECEMBER"]},
  {"name":"flare.crop.Cauliflower","size":3534,"imports":["flare.month.JANUARY","flare.month.FEBRUARY","flare.month.OCTOBER","flare.month.NOVEMBER","flare.month.DECEMBER"]},
  {"name":"flare.crop.Celery","size":3534,"imports":["flare.month.JANUARY","flare.month.AUGUST","flare.month.SEPTEMBER","flare.month.OCTOBER","flare.month.NOVEMBER","flare.month.DECEMBER"]},
  {"name":"flare.crop.Chives","size":3534,"imports":["flare.month.JANUARY","flare.month.FEBRUARY","flare.month.MARCH","flare.month.OCTOBER","flare.month.NOVEMBER","flare.month.DECEMBER"]},
  {"name":"flare.crop.Collards","size":3534,"imports":["flare.month.JANUARY","flare.month.FEBRUARY","flare.month.MARCH","flare.month.OCTOBER","flare.month.NOVEMBER","flare.month.DECEMBER"]},
  {"name":"flare.crop.Corn","size":3534,"imports":["flare.month.APRIL","flare.month.MAY","flare.month.APRIL","flare.month.MAY","flare.month.JUNE","flare.month.JULY","flare.month.AUGUST"]},
  {"name":"flare.crop.Cucumbers","size":3534,"imports":["flare.month.APRIL","flare.month.MAY","flare.month.APRIL","flare.month.MAY","flare.month.JUNE","flare.month.JULY","flare.month.AUGUST"]},
  {"name":"flare.crop.Eggplant","size":3534,"imports":["flare.month.APRIL","flare.month.MAY"]},
  {"name":"flare.crop.Endive","size":3534,"imports":["flare.month.JANUARY","flare.month.FEBRUARY","flare.month.MARCH","flare.month.OCTOBER","flare.month.NOVEMBER","flare.month.DECEMBER"]},
  {"name":"flare.crop.Favas","size":3534,"imports":["flare.month.JANUARY","flare.month.OCTOBER","flare.month.NOVEMBER","flare.month.DECEMBER"]},
  {"name":"flare.crop.Jicama","size":3534,"imports":["flare.month.APRIL","flare.month.MAY"]},
  {"name":"flare.crop.Kale","size":3534,"imports":["flare.month.JANUARY","flare.month.FEBRUARY","flare.month.MARCH","flare.month.OCTOBER","flare.month.NOVEMBER","flare.month.DECEMBER"]},
  {"name":"flare.crop.Kohlrabi","size":3534,"imports":["flare.month.JANUARY","flare.month.FEBRUARY","flare.month.MARCH","flare.month.OCTOBER","flare.month.NOVEMBER","flare.month.DECEMBER"]},
  {"name":"flare.crop.Leeks","size":3534,"imports":["flare.month.JANUARY","flare.month.FEBRUARY","flare.month.SEPTEMBER","flare.month.OCTOBER","flare.month.NOVEMBER","flare.month.DECEMBER"]},
  {"name":"flare.crop.Lettuce","size":3534,"imports":["flare.month.JANUARY","flare.month.FEBRUARY","flare.month.MARCH","flare.month.OCTOBER","flare.month.NOVEMBER","flare.month.DECEMBER"]},
  {"name":"flare.crop.LimaBeans","size":3534,"imports":["flare.month.APRIL","flare.month.MAY","flare.month.APRIL","flare.month.MAY","flare.month.JUNE","flare.month.JULY","flare.month.AUGUST"]},
  {"name":"flare.crop.Mustard","size":3534,"imports":["flare.month.JANUARY","flare.month.FEBRUARY","flare.month.MARCH","flare.month.OCTOBER","flare.month.NOVEMBER","flare.month.DECEMBER"]},
  {"name":"flare.crop.Okra","size":3534,"imports":["flare.month.APRIL","flare.month.MAY","flare.month.JUNE"]},
  {"name":"flare.crop.Onions","size":3534,"imports":["flare.month.JANUARY","flare.month.FEBRUARY","flare.month.NOVEMBER","flare.month.DECEMBER"]},
  {"name":"flare.crop.Parsley","size":3534,"imports":["flare.month.JANUARY","flare.month.FEBRUARY","flare.month.MARCH","flare.month.OCTOBER","flare.month.NOVEMBER","flare.month.DECEMBER"]},
  {"name":"flare.crop.Parsnip","size":3534,"imports":["flare.month.JANUARY","flare.month.FEBRUARY","flare.month.OCTOBER","flare.month.NOVEMBER","flare.month.DECEMBER"]},
  {"name":"flare.crop.Peas","size":3534,"imports":["flare.month.JANUARY","flare.month.FEBRUARY","flare.month.MARCH","flare.month.OCTOBER","flare.month.NOVEMBER","flare.month.DECEMBER"]},
  {"name":"flare.crop.Peppers","size":3534,"imports":["flare.month.APRIL","flare.month.MAY","flare.month.JUNE"]},
  {"name":"flare.crop.Potatoes","size":3534,"imports":["flare.month.JANUARY","flare.month.FEBRUARY","flare.month.MARCH","flare.month.APRIL","flare.month.MAY","flare.month.APRIL","flare.month.MAY","flare.month.JUNE"]},
  {"name":"flare.crop.Pumpkin","size":3534,"imports":["flare.month.APRIL","flare.month.MAY","flare.month.JUNE"]},
  {"name":"flare.crop.Radish","size":3534,"imports":["flare.month.JANUARY","flare.month.FEBRUARY","flare.month.MARCH","flare.month.APRIL","flare.month.MAY","flare.month.APRIL","flare.month.MAY","flare.month.JUNE","flare.month.JULY","flare.month.AUGUST","flare.month.SEPTEMBER","flare.month.OCTOBER","flare.month.NOVEMBER","flare.month.DECEMBER"]},
  {"name":"flare.crop.Rutabaga","size":3534,"imports":["flare.month.JANUARY","flare.month.FEBRUARY","flare.month.MARCH","flare.month.OCTOBER","flare.month.NOVEMBER","flare.month.DECEMBER"]},
  {"name":"flare.crop.Spinach","size":3534,"imports":["flare.month.JANUARY","flare.month.FEBRUARY","flare.month.MARCH","flare.month.OCTOBER","flare.month.NOVEMBER","flare.month.DECEMBER"]},
  {"name":"flare.crop.Squash.Summer","size":3534,"imports":["flare.month.FEBRUARY","flare.month.MARCH","flare.month.APRIL","flare.month.MAY","flare.month.APRIL","flare.month.MAY","flare.month.JUNE","flare.month.JULY","flare.month.AUGUST","flare.month.SEPTEMBER"]},
  {"name":"flare.crop.Squash.Winter","size":3534,"imports":["flare.month.MARCH","flare.month.APRIL","flare.month.MAY","flare.month.APRIL","flare.month.MAY","flare.month.JUNE"]},
  {"name":"flare.crop.Sunflowers","size":3534,"imports":["flare.month.MARCH","flare.month.APRIL","flare.month.MAY","flare.month.APRIL","flare.month.MAY","flare.month.JUNE"]},
  {"name":"flare.crop.SwissChard","size":3534,"imports":["flare.month.JANUARY","flare.month.FEBRUARY","flare.month.MARCH","flare.month.APRIL","flare.month.MAY","flare.month.APRIL","flare.month.MAY","flare.month.JUNE","flare.month.JULY","flare.month.AUGUST","flare.month.SEPTEMBER","flare.month.OCTOBER","flare.month.NOVEMBER","flare.month.DECEMBER"]},
  {"name":"flare.crop.Tomatoes","size":3534,"imports":["flare.month.MARCH","flare.month.APRIL","flare.month.MAY","flare.month.APRIL","flare.month.MAY","flare.month.JUNE","flare.month.JULY"]},
  {"name":"flare.crop.Turnips","size":3534,"imports":["flare.month.JANUARY","flare.month.FEBRUARY","flare.month.MARCH","flare.month.OCTOBER","flare.month.NOVEMBER","flare.month.DECEMBER"]},
  {"name":"flare.crop.Watermelon","size":3534,"imports":["flare.month.APRIL","flare.month.MAY","flare.month.JUNE"]},
  {"name":"flare.crop.WinterZucchini","size":3534,"imports":["flare.month.SEPTEMBER","flare.month.OCTOBER"]}
  ]